legoai/__init__.py
legoai/config.yaml
legoai/core/__init__.py
legoai/core/configuration.py
legoai/core/logger.py
legoai/core/utils.py
legoai/model/dependant/datatype_l1_identification/en-80k.txt
legoai/model/model_objects/datatype_l1_identification/di_l1_classifier_encoder_13052023.pkl
legoai/model/model_objects/datatype_l1_identification/di_l1_classifier_encoder_22042023.pkl
legoai/model/model_objects/datatype_l1_identification/di_l1_classifier_encoder_25042023.pkl
legoai/model/model_objects/datatype_l1_identification/di_l1_classifier_xgb_13052023.pkl
legoai/model/model_objects/datatype_l1_identification/di_l1_classifier_xgb_22042023.pkl
legoai/model/model_objects/datatype_l1_identification/di_l1_classifier_xgb_25042023.pkl
legoai/modules/__init__.py
legoai/modules/datatype_identification/__init__.py
legoai/modules/datatype_identification/custom_features.py
legoai/modules/datatype_identification/functional.py
legoai/modules/datatype_identification/l1_model.py
legoai/modules/datatype_identification/l2_model.py
legoai/modules/datatype_identification/pipeline.py
legoai/modules/datatype_identification/preprocessing.py
legoai/modules/datatype_identification/utils.py
legoai-0.3.dist-info/LICENSE
legoai-0.3.dist-info/METADATA
legoai-0.3.dist-info/WHEEL
legoai-0.3.dist-info/top_level.txt
legoai-0.3.dist-info/RECORD
