Metadata-Version: 2.1
Name: legoai
Version: 0.3
Summary: An open-source package from LEGOAI for identifying data types
Home-page: https://github.com/LEGOAI-TECHNOLOGIES/Data-Type-Identifier
Author: LEGOAI Team
Author-email: contactus@legoai.com
License: MIT
Classifier: License :: OSI Approved :: MIT License
Classifier: Programming Language :: Python :: 3.10
Classifier: Operating System :: OS Independent
Classifier: Environment :: Console
Requires-Python: >=3.10
License-File: LICENSE
Requires-Dist: aiohttp ==3.9.3
Requires-Dist: aiosignal ==1.3.1
Requires-Dist: async-timeout ==4.0.3
Requires-Dist: attrs ==23.2.0
Requires-Dist: certifi ==2023.11.17
Requires-Dist: charset-normalizer ==3.3.2
Requires-Dist: click ==8.1.7
Requires-Dist: dataclasses-json ==0.5.14
Requires-Dist: dill ==0.3.7
Requires-Dist: editdistpy ==0.1.3
Requires-Dist: frozenlist ==1.4.1
Requires-Dist: greenlet ==3.0.3
Requires-Dist: idna ==3.6
Requires-Dist: joblib ==1.3.2
Requires-Dist: langchain ==0.0.258
Requires-Dist: langsmith ==0.0.83
Requires-Dist: marshmallow ==3.20.2
Requires-Dist: multidict ==6.0.4
Requires-Dist: mypy-extensions ==1.0.0
Requires-Dist: nltk ==3.8.1
Requires-Dist: numexpr ==2.8.8
Requires-Dist: numpy ==1.26.3
Requires-Dist: openai ==0.27.8
Requires-Dist: openapi-schema-pydantic ==1.2.4
Requires-Dist: packaging ==23.2
Requires-Dist: pandas ==2.2.0
Requires-Dist: pydantic ==1.10.14
Requires-Dist: pyfunctional ==1.4.2
Requires-Dist: python-dateutil ==2.8.2
Requires-Dist: python-dotenv ==1.0.0
Requires-Dist: pytz ==2023.3.post1
Requires-Dist: PyYAML ==6.0.1
Requires-Dist: regex ==2023.12.25
Requires-Dist: requests ==2.31.0
Requires-Dist: scikit-learn ==1.2.2
Requires-Dist: scipy ==1.11.4
Requires-Dist: six ==1.16.0
Requires-Dist: SQLAlchemy ==2.0.25
Requires-Dist: symspellpy ==6.7.7
Requires-Dist: tabulate ==0.9.0
Requires-Dist: tenacity ==8.2.3
Requires-Dist: threadpoolctl ==3.2.0
Requires-Dist: tqdm ==4.66.1
Requires-Dist: trieregex ==1.0.0
Requires-Dist: typing-inspect ==0.9.0
Requires-Dist: typing-extensions ==4.9.0
Requires-Dist: tzdata ==2023.4
Requires-Dist: urllib3 ==2.1.0
Requires-Dist: xgboost ==1.7.5
Requires-Dist: yarl ==1.9.4
Provides-Extra: dev
Requires-Dist: twine >=4.0.2 ; extra == 'dev'
